index.py
aws_public_endpoints-1.3.0.dist-info/METADATA
aws_public_endpoints-1.3.0.dist-info/WHEEL
aws_public_endpoints-1.3.0.dist-info/entry_points.txt
aws_public_endpoints-1.3.0.dist-info/top_level.txt
aws_public_endpoints-1.3.0.dist-info/RECORD
