Metadata-Version: 2.4
Name: aws-public-endpoints
Version: 1.3.0
Summary: AWS Public Endpoints Scanner MCP Server
Author-email: Hyeonggeun Oh <kandy@plaintexting.com>
License: MIT
Keywords: aws,public-endpoints,security,mcp,infrastructure
Classifier: Development Status :: 4 - Beta
Classifier: Intended Audience :: Developers
Classifier: License :: OSI Approved :: MIT License
Classifier: Programming Language :: Python :: 3
Classifier: Programming Language :: Python :: 3.10
Classifier: Programming Language :: Python :: 3.11
Classifier: Programming Language :: Python :: 3.12
Classifier: Topic :: Software Development :: Libraries :: Python Modules
Classifier: Topic :: System :: Systems Administration
Classifier: Topic :: Security
Requires-Python: >=3.10
Requires-Dist: mcp>=1.0.0
Requires-Dist: boto3>=1.40.0
